usdt_wallet_manager/__init__.py
usdt_wallet_manager/transactions.py
usdt_wallet_manager-0.1.dist-info/METADATA
usdt_wallet_manager-0.1.dist-info/WHEEL
usdt_wallet_manager-0.1.dist-info/entry_points.txt
usdt_wallet_manager-0.1.dist-info/top_level.txt
usdt_wallet_manager-0.1.dist-info/RECORD
